pqlattice/__init__.py
pqlattice/_utils.py
pqlattice/py.typed
pqlattice/settings.py
pqlattice/_backends/__init__.py
pqlattice/_backends/_fast.py
pqlattice/_backends/_native.py
pqlattice/_backends/_protocol.py
pqlattice/integer/__init__.py
pqlattice/integer/_integer.py
pqlattice/integer/_modintring.py
pqlattice/integer/_modring.py
pqlattice/integer/_primality.py
pqlattice/integer/_primes.py
pqlattice/lattice/__init__.py
pqlattice/lattice/_bkz.py
pqlattice/lattice/_cvp.py
pqlattice/lattice/_embeddings.py
pqlattice/lattice/_gso.py
pqlattice/lattice/_hkz.py
pqlattice/lattice/_lattice.py
pqlattice/lattice/_lll.py
pqlattice/lattice/_svp.py
pqlattice/lattice/embeddings.py
pqlattice/linalg/__init__.py
pqlattice/linalg/_linalg.py
pqlattice/linalg/_modint.py
pqlattice/linalg/_utils.py
pqlattice/polynomial/__init__.py
pqlattice/polynomial/_modpolyqring.py
pqlattice/polynomial/_modpolyring.py
pqlattice/polynomial/_poly.py
pqlattice/polynomial/poly.py
pqlattice/random/__init__.py
pqlattice/random/_distribution.py
pqlattice/random/_lattice.py
pqlattice/random/_lwe.py
pqlattice/random/_lwr.py
pqlattice/random/_prime.py
pqlattice/random/distribution.py
pqlattice/typing/__init__.py
pqlattice/typing/_types.py
pqlattice/typing/_types_validator.py
pqlattice-0.1.2.dist-info/METADATA
pqlattice-0.1.2.dist-info/WHEEL
pqlattice-0.1.2.dist-info/licenses/LICENSE
pqlattice-0.1.2.dist-info/RECORD
