Metadata-Version: 2.4
Name: pqlattice
Version: 0.1.2
Summary: Add your description here
Project-URL: Repository, https://github.com/MikolajLH/pqlattice.git
Project-URL: Documentation, https://mikolajlh.github.io/pqlattice/
Author-email: Mikołaj Leonhardt <mikolaj.leonhardt@gmail.com>
License: Copyright (c) 2026, Mikołaj Leonhardt
License-File: LICENSE
Keywords: cryptography,lattice
Classifier: Intended Audience :: Education
Classifier: License :: OSI Approved :: MIT License
Classifier: Operating System :: OS Independent
Classifier: Programming Language :: Python :: 3
Classifier: Topic :: Security :: Cryptography
Requires-Python: >=3.12
Requires-Dist: numpy>=1.26
Provides-Extra: fast
Requires-Dist: cysignals>=1.12.6; extra == 'fast'
Requires-Dist: fpylll>=0.6.4; extra == 'fast'
Requires-Dist: python-flint>=0.8.0; extra == 'fast'
